README.md
setup.py
mmappickle/__init__.py
mmappickle/dict.py
mmappickle/http.py
mmappickle/utils.py
mmappickle.egg-info/PKG-INFO
mmappickle.egg-info/SOURCES.txt
mmappickle.egg-info/dependency_links.txt
mmappickle.egg-info/top_level.txt
mmappickle/picklers/__init__.py
mmappickle/picklers/base.py
mmappickle/picklers/numpy.py
mmappickle/stubs/__init__.py
mmappickle/stubs/numpy.py