Metadata-Version: 1.0
Name: mmappickle
Version: 1.0.0
Summary: This module enables to store large structures in a python pickle, in such a way that the data can be mmap'ed instead of being copied in memory.
Home-page: https://github.com/UniNE-CHYN/mmappickle
Author: Laurent Fasnacht
Author-email: l@libres.ch
License: UNKNOWN
Platform: UNKNOWN
